casa_formats_io/_casa_chunking.abi3.so
casa_formats_io/casa_dask.py
casa_formats_io/version.py
casa_formats_io/casa_wcs.py
casa_formats_io/glue_factory.py
casa_formats_io/__init__.py
casa_formats_io/table_reader.py
casa_formats_io/casa_low_level_io/record.py
casa_formats_io/casa_low_level_io/casa_functions.py
casa_formats_io/casa_low_level_io/core.py
casa_formats_io/casa_low_level_io/table.py
casa_formats_io/casa_low_level_io/__init__.py
casa_formats_io/casa_low_level_io/utils.py
casa_formats_io/casa_low_level_io/dask_mixin.py
casa_formats_io/casa_low_level_io/data_managers/aipsio.py
casa_formats_io/casa_low_level_io/data_managers/incremental.py
casa_formats_io/casa_low_level_io/data_managers/standard.py
casa_formats_io/casa_low_level_io/data_managers/__init__.py
casa_formats_io/casa_low_level_io/data_managers/tiled.py
casa_formats_io/casa_low_level_io/tests/__init__.py
casa_formats_io/casa_low_level_io/tests/test_casa_low_level_io.py
casa_formats_io/casa_low_level_io/tests/data/lt32bit.image/table.f0
casa_formats_io/casa_low_level_io/tests/data/floatarray.image/table.dat
casa_formats_io/casa_low_level_io/tests/data/gt32bit.image/table.f0
casa_formats_io/casa_low_level_io/tests/data/simple.ms/table.lock
casa_formats_io/casa_low_level_io/tests/data/simple.ms/table.f5
casa_formats_io/casa_low_level_io/tests/data/simple.ms/table.f7
casa_formats_io/casa_low_level_io/tests/data/simple.ms/table.f18
casa_formats_io/casa_low_level_io/tests/data/simple.ms/table.f19_TSM0
casa_formats_io/casa_low_level_io/tests/data/simple.ms/table.f3
casa_formats_io/casa_low_level_io/tests/data/simple.ms/table.f17_TSM2
casa_formats_io/casa_low_level_io/tests/data/simple.ms/table.f10
casa_formats_io/casa_low_level_io/tests/data/simple.ms/table.f20
casa_formats_io/casa_low_level_io/tests/data/simple.ms/table.f9
casa_formats_io/casa_low_level_io/tests/data/simple.ms/table.f14
casa_formats_io/casa_low_level_io/tests/data/simple.ms/table.f6
casa_formats_io-0.3.0.dist-info/LICENSE
casa_formats_io-0.3.0.dist-info/METADATA
casa_formats_io-0.3.0.dist-info/RECORD
casa_formats_io-0.3.0.dist-info/top_level.txt
casa_formats_io-0.3.0.dist-info/entry_points.txt
casa_formats_io-0.3.0.dist-info/WHEEL
