Metadata-Version: 2.1
Name: casa-formats-io
Version: 0.3.0
Summary: Dask-based reader for CASA data
Home-page: http://casa-formats-io.readthedocs.org
Author: Thomas Robitaille, Adam Ginsburg, and Eric Koch
Author-email: thomas.robitaille@gmail.com
License: LGPLv2
Requires-Python: >=3.9
License-File: LICENSE
Requires-Dist: astropy >=4.0
Requires-Dist: numpy >=1.21
Requires-Dist: dask[array] >=2.0
Provides-Extra: casa
Requires-Dist: casatools >=6.2.0.12 ; extra == 'casa'
Provides-Extra: docs
Requires-Dist: numpydoc ; extra == 'docs'
Requires-Dist: sphinx-automodapi ; extra == 'docs'
Provides-Extra: test
Requires-Dist: pytest ; extra == 'test'
Requires-Dist: pytest-cov ; extra == 'test'
